{"directed": false, "graph": {}, "nodes": [{"level": 2, "edge_list": [{"graph": 142, "neighbor": 5679}], "edge": true, "y": 8.0, "x": 2.8000000000000003, "id": 5680}, {"y": 8.1, "x": 2.8000000000000003, "edge": false, "id": 5681, "level": 2}, {"y": 8.200000000000001, "x": 2.8000000000000003, "edge": false, "id": 5682, "level": 3}, {"y": 8.3, "x": 2.8000000000000003, "edge": false, "id": 5683, "level": 3}, {"y": 8.4, "x": 2.8000000000000003, "edge": false, "id": 5684, "level": 2}, {"y": 8.5, "x": 2.8000000000000003, "edge": false, "id": 5685, "level": 3}, {"y": 8.6, "x": 2.8000000000000003, "edge": false, "id": 5686, "level": 2}, {"y": 8.700000000000001, "x": 2.8000000000000003, "edge": false, "id": 5687, "level": 2}, {"y": 8.8, "x": 2.8000000000000003, "edge": false, "id": 5688, "level": 3}, {"level": 3, "edge_list": [{"graph": 182, "neighbor": 5690}], "edge": true, "y": 8.9, "x": 2.8000000000000003, "id": 5689}, {"level": 2, "edge_list": [{"graph": 142, "neighbor": 4679}], "edge": true, "y": 8.0, "x": 2.3000000000000003, "id": 4680}, {"y": 8.1, "x": 2.3000000000000003, "edge": false, "id": 4681, "level": 2}, {"y": 8.200000000000001, "x": 2.3000000000000003, "edge": false, "id": 4682, "level": 2}, {"y": 8.3, "x": 2.3000000000000003, "edge": false, "id": 4683, "level": 3}, {"y": 8.4, "x": 2.3000000000000003, "edge": false, "id": 4684, "level": 3}, {"y": 8.5, "x": 2.3000000000000003, "edge": false, "id": 4685, "level": 3}, {"y": 8.6, "x": 2.3000000000000003, "edge": false, "id": 4686, "level": 2}, {"y": 8.700000000000001, "x": 2.3000000000000003, "edge": false, "id": 4687, "level": 3}, {"y": 8.8, "x": 2.3000000000000003, "edge": false, "id": 4688, "level": 3}, {"level": 2, "edge_list": [{"graph": 182, "neighbor": 4690}], "edge": true, "y": 8.9, "x": 2.3000000000000003, "id": 4689}, {"level": 3, "edge_list": [{"graph": 142, "neighbor": 5279}], "edge": true, "y": 8.0, "x": 2.6, "id": 5280}, {"y": 8.1, "x": 2.6, "edge": false, "id": 5281, "level": 2}, {"y": 8.200000000000001, "x": 2.6, "edge": false, "id": 5282, "level": 2}, {"y": 8.3, "x": 2.6, "edge": false, "id": 5283, "level": 3}, {"y": 8.4, "x": 2.6, "edge": false, "id": 5284, "level": 3}, {"y": 8.5, "x": 2.6, "edge": false, "id": 5285, "level": 2}, {"y": 8.6, "x": 2.6, "edge": false, "id": 5286, "level": 3}, {"y": 8.700000000000001, "x": 2.6, "edge": false, "id": 5287, "level": 3}, {"y": 8.8, "x": 2.6, "edge": false, "id": 5288, "level": 3}, {"level": 3, "edge_list": [{"graph": 182, "neighbor": 5290}], "edge": true, "y": 8.9, "x": 2.6, "id": 5289}, {"level": 2, "edge_list": [{"graph": 142, "neighbor": 4279}], "edge": true, "y": 8.0, "x": 2.1, "id": 4280}, {"y": 8.1, "x": 2.1, "edge": false, "id": 4281, "level": 3}, {"y": 8.200000000000001, "x": 2.1, "edge": false, "id": 4282, "level": 2}, {"y": 8.3, "x": 2.1, "edge": false, "id": 4283, "level": 3}, {"y": 8.4, "x": 2.1, "edge": false, "id": 4284, "level": 3}, {"y": 8.5, "x": 2.1, "edge": false, "id": 4285, "level": 3}, {"y": 8.6, "x": 2.1, "edge": false, "id": 4286, "level": 3}, {"y": 8.700000000000001, "x": 2.1, "edge": false, "id": 4287, "level": 2}, {"y": 8.8, "x": 2.1, "edge": false, "id": 4288, "level": 2}, {"level": 2, "edge_list": [{"graph": 182, "neighbor": 4290}], "edge": true, "y": 8.9, "x": 2.1, "id": 4289}, {"level": 2, "edge_list": [{"graph": 142, "neighbor": 5879}, {"graph": 163, "neighbor": 6080}], "edge": true, "y": 8.0, "x": 2.9000000000000004, "id": 5880}, {"level": 3, "edge_list": [{"graph": 163, "neighbor": 6081}], "edge": true, "y": 8.1, "x": 2.9000000000000004, "id": 5881}, {"level": 3, "edge_list": [{"graph": 163, "neighbor": 6082}], "edge": true, "y": 8.200000000000001, "x": 2.9000000000000004, "id": 5882}, {"level": 2, "edge_list": [{"graph": 163, "neighbor": 6083}], "edge": true, "y": 8.3, "x": 2.9000000000000004, "id": 5883}, {"level": 3, "edge_list": [{"graph": 163, "neighbor": 6084}], "edge": true, "y": 8.4, "x": 2.9000000000000004, "id": 5884}, {"level": 3, "edge_list": [{"graph": 163, "neighbor": 6085}], "edge": true, "y": 8.5, "x": 2.9000000000000004, "id": 5885}, {"level": 2, "edge_list": [{"graph": 163, "neighbor": 6086}], "edge": true, "y": 8.6, "x": 2.9000000000000004, "id": 5886}, {"level": 3, "edge_list": [{"graph": 163, "neighbor": 6087}], "edge": true, "y": 8.700000000000001, "x": 2.9000000000000004, "id": 5887}, {"level": 3, "edge_list": [{"graph": 163, "neighbor": 6088}], "edge": true, "y": 8.8, "x": 2.9000000000000004, "id": 5888}, {"level": 3, "edge_list": [{"graph": 182, "neighbor": 5890}, {"graph": 163, "neighbor": 6089}], "edge": true, "y": 8.9, "x": 2.9000000000000004, "id": 5889}, {"level": 2, "edge_list": [{"graph": 142, "neighbor": 4879}], "edge": true, "y": 8.0, "x": 2.4000000000000004, "id": 4880}, {"y": 8.1, "x": 2.4000000000000004, "edge": false, "id": 4881, "level": 3}, {"y": 8.200000000000001, "x": 2.4000000000000004, "edge": false, "id": 4882, "level": 2}, {"y": 8.3, "x": 2.4000000000000004, "edge": false, "id": 4883, "level": 2}, {"y": 8.4, "x": 2.4000000000000004, "edge": false, "id": 4884, "level": 3}, {"y": 8.5, "x": 2.4000000000000004, "edge": false, "id": 4885, "level": 2}, {"y": 8.6, "x": 2.4000000000000004, "edge": false, "id": 4886, "level": 2}, {"y": 8.700000000000001, "x": 2.4000000000000004, "edge": false, "id": 4887, "level": 3}, {"y": 8.8, "x": 2.4000000000000004, "edge": false, "id": 4888, "level": 3}, {"level": 3, "edge_list": [{"graph": 182, "neighbor": 4890}], "edge": true, "y": 8.9, "x": 2.4000000000000004, "id": 4889}, {"level": 3, "edge_list": [{"graph": 142, "neighbor": 5479}], "edge": true, "y": 8.0, "x": 2.7, "id": 5480}, {"y": 8.1, "x": 2.7, "edge": false, "id": 5481, "level": 3}, {"y": 8.200000000000001, "x": 2.7, "edge": false, "id": 5482, "level": 3}, {"y": 8.3, "x": 2.7, "edge": false, "id": 5483, "level": 2}, {"y": 8.4, "x": 2.7, "edge": false, "id": 5484, "level": 2}, {"y": 8.5, "x": 2.7, "edge": false, "id": 5485, "level": 3}, {"y": 8.6, "x": 2.7, "edge": false, "id": 5486, "level": 2}, {"y": 8.700000000000001, "x": 2.7, "edge": false, "id": 5487, "level": 2}, {"y": 8.8, "x": 2.7, "edge": false, "id": 5488, "level": 2}, {"level": 3, "edge_list": [{"graph": 182, "neighbor": 5490}], "edge": true, "y": 8.9, "x": 2.7, "id": 5489}, {"level": 3, "edge_list": [{"graph": 142, "neighbor": 4479}], "edge": true, "y": 8.0, "x": 2.2, "id": 4480}, {"y": 8.1, "x": 2.2, "edge": false, "id": 4481, "level": 3}, {"y": 8.200000000000001, "x": 2.2, "edge": false, "id": 4482, "level": 3}, {"y": 8.3, "x": 2.2, "edge": false, "id": 4483, "level": 3}, {"y": 8.4, "x": 2.2, "edge": false, "id": 4484, "level": 2}, {"y": 8.5, "x": 2.2, "edge": false, "id": 4485, "level": 3}, {"y": 8.6, "x": 2.2, "edge": false, "id": 4486, "level": 3}, {"y": 8.700000000000001, "x": 2.2, "edge": false, "id": 4487, "level": 2}, {"y": 8.8, "x": 2.2, "edge": false, "id": 4488, "level": 2}, {"level": 2, "edge_list": [{"graph": 182, "neighbor": 4490}], "edge": true, "y": 8.9, "x": 2.2, "id": 4489}, {"level": 3, "edge_list": [{"graph": 142, "neighbor": 5079}], "edge": true, "y": 8.0, "x": 2.5, "id": 5080}, {"y": 8.1, "x": 2.5, "edge": false, "id": 5081, "level": 3}, {"y": 8.200000000000001, "x": 2.5, "edge": false, "id": 5082, "level": 3}, {"y": 8.3, "x": 2.5, "edge": false, "id": 5083, "level": 3}, {"y": 8.4, "x": 2.5, "edge": false, "id": 5084, "level": 2}, {"y": 8.5, "x": 2.5, "edge": false, "id": 5085, "level": 2}, {"y": 8.6, "x": 2.5, "edge": false, "id": 5086, "level": 3}, {"y": 8.700000000000001, "x": 2.5, "edge": false, "id": 5087, "level": 3}, {"y": 8.8, "x": 2.5, "edge": false, "id": 5088, "level": 3}, {"level": 3, "edge_list": [{"graph": 182, "neighbor": 5090}], "edge": true, "y": 8.9, "x": 2.5, "id": 5089}, {"level": 3, "edge_list": [{"graph": 142, "neighbor": 4079}, {"graph": 161, "neighbor": 3880}], "edge": true, "y": 8.0, "x": 2.0, "id": 4080}, {"level": 3, "edge_list": [{"graph": 161, "neighbor": 3881}], "edge": true, "y": 8.1, "x": 2.0, "id": 4081}, {"level": 3, "edge_list": [{"graph": 161, "neighbor": 3882}], "edge": true, "y": 8.200000000000001, "x": 2.0, "id": 4082}, {"level": 3, "edge_list": [{"graph": 161, "neighbor": 3883}], "edge": true, "y": 8.3, "x": 2.0, "id": 4083}, {"level": 3, "edge_list": [{"graph": 161, "neighbor": 3884}], "edge": true, "y": 8.4, "x": 2.0, "id": 4084}, {"level": 3, "edge_list": [{"graph": 161, "neighbor": 3885}], "edge": true, "y": 8.5, "x": 2.0, "id": 4085}, {"level": 3, "edge_list": [{"graph": 161, "neighbor": 3886}], "edge": true, "y": 8.6, "x": 2.0, "id": 4086}, {"level": 2, "edge_list": [{"graph": 161, "neighbor": 3887}], "edge": true, "y": 8.700000000000001, "x": 2.0, "id": 4087}, {"level": 3, "edge_list": [{"graph": 161, "neighbor": 3888}], "edge": true, "y": 8.8, "x": 2.0, "id": 4088}, {"level": 2, "edge_list": [{"graph": 161, "neighbor": 3889}, {"graph": 182, "neighbor": 4090}], "edge": true, "y": 8.9, "x": 2.0, "id": 4089}], "links": [{"source": 5680, "target": 5480, "weight": 3}, {"source": 5680, "target": 5681, "weight": 2}, {"source": 5680, "target": 5880, "weight": 2}, {"source": 5681, "target": 5481, "weight": 3}, {"source": 5681, "target": 5682, "weight": 3}, {"source": 5681, "target": 5881, "weight": 3}, {"source": 5682, "target": 5482, "weight": 3}, {"source": 5682, "target": 5683, "weight": 3}, {"source": 5682, "target": 5882, "weight": 3}, {"source": 5683, "target": 5483, "weight": 3}, {"source": 5683, "target": 5684, "weight": 3}, {"source": 5683, "target": 5883, "weight": 3}, {"source": 5684, "target": 5884, "weight": 3}, {"source": 5684, "target": 5484, "weight": 2}, {"source": 5684, "target": 5685, "weight": 3}, {"source": 5685, "target": 5485, "weight": 3}, {"source": 5685, "target": 5686, "weight": 3}, {"source": 5685, "target": 5885, "weight": 3}, {"source": 5686, "target": 5886, "weight": 2}, {"source": 5686, "target": 5486, "weight": 2}, {"source": 5686, "target": 5687, "weight": 2}, {"source": 5687, "target": 5688, "weight": 3}, {"source": 5687, "target": 5887, "weight": 3}, {"source": 5687, "target": 5487, "weight": 2}, {"source": 5688, "target": 5488, "weight": 3}, {"source": 5688, "target": 5689, "weight": 3}, {"source": 5688, "target": 5888, "weight": 3}, {"source": 5689, "target": 5489, "weight": 3}, {"source": 5689, "target": 5889, "weight": 3}, {"source": 4680, "target": 4480, "weight": 3}, {"source": 4680, "target": 4681, "weight": 2}, {"source": 4680, "target": 4880, "weight": 2}, {"source": 4681, "target": 4481, "weight": 3}, {"source": 4681, "target": 4682, "weight": 2}, {"source": 4681, "target": 4881, "weight": 3}, {"source": 4682, "target": 4482, "weight": 3}, {"source": 4682, "target": 4683, "weight": 3}, {"source": 4682, "target": 4882, "weight": 2}, {"source": 4683, "target": 4883, "weight": 3}, {"source": 4683, "target": 4483, "weight": 3}, {"source": 4683, "target": 4684, "weight": 3}, {"source": 4684, "target": 4884, "weight": 3}, {"source": 4684, "target": 4484, "weight": 3}, {"source": 4684, "target": 4685, "weight": 3}, {"source": 4685, "target": 4485, "weight": 3}, {"source": 4685, "target": 4686, "weight": 3}, {"source": 4685, "target": 4885, "weight": 3}, {"source": 4686, "target": 4886, "weight": 2}, {"source": 4686, "target": 4486, "weight": 3}, {"source": 4686, "target": 4687, "weight": 3}, {"source": 4687, "target": 4688, "weight": 3}, {"source": 4687, "target": 4887, "weight": 3}, {"source": 4687, "target": 4487, "weight": 3}, {"source": 4688, "target": 4488, "weight": 3}, {"source": 4688, "target": 4689, "weight": 3}, {"source": 4688, "target": 4888, "weight": 3}, {"source": 4689, "target": 4489, "weight": 2}, {"source": 4689, "target": 4889, "weight": 3}, {"source": 5280, "target": 5080, "weight": 3}, {"source": 5280, "target": 5281, "weight": 3}, {"source": 5280, "target": 5480, "weight": 3}, {"source": 5281, "target": 5081, "weight": 3}, {"source": 5281, "target": 5282, "weight": 2}, {"source": 5281, "target": 5481, "weight": 3}, {"source": 5282, "target": 5082, "weight": 3}, {"source": 5282, "target": 5283, "weight": 3}, {"source": 5282, "target": 5482, "weight": 3}, {"source": 5283, "target": 5083, "weight": 3}, {"source": 5283, "target": 5284, "weight": 3}, {"source": 5283, "target": 5483, "weight": 3}, {"source": 5284, "target": 5484, "weight": 3}, {"source": 5284, "target": 5084, "weight": 3}, {"source": 5284, "target": 5285, "weight": 3}, {"source": 5285, "target": 5085, "weight": 2}, {"source": 5285, "target": 5286, "weight": 3}, {"source": 5285, "target": 5485, "weight": 3}, {"source": 5286, "target": 5287, "weight": 3}, {"source": 5286, "target": 5086, "weight": 3}, {"source": 5286, "target": 5486, "weight": 3}, {"source": 5287, "target": 5288, "weight": 3}, {"source": 5287, "target": 5487, "weight": 3}, {"source": 5287, "target": 5087, "weight": 3}, {"source": 5288, "target": 5088, "weight": 3}, {"source": 5288, "target": 5289, "weight": 3}, {"source": 5288, "target": 5488, "weight": 3}, {"source": 5289, "target": 5089, "weight": 3}, {"source": 5289, "target": 5489, "weight": 3}, {"source": 4280, "target": 4080, "weight": 3}, {"source": 4280, "target": 4281, "weight": 3}, {"source": 4280, "target": 4480, "weight": 3}, {"source": 4281, "target": 4081, "weight": 3}, {"source": 4281, "target": 4282, "weight": 3}, {"source": 4281, "target": 4481, "weight": 3}, {"source": 4282, "target": 4082, "weight": 3}, {"source": 4282, "target": 4283, "weight": 3}, {"source": 4282, "target": 4482, "weight": 3}, {"source": 4283, "target": 4284, "weight": 3}, {"source": 4283, "target": 4083, "weight": 3}, {"source": 4283, "target": 4483, "weight": 3}, {"source": 4284, "target": 4484, "weight": 3}, {"source": 4284, "target": 4084, "weight": 3}, {"source": 4284, "target": 4285, "weight": 3}, {"source": 4285, "target": 4085, "weight": 3}, {"source": 4285, "target": 4286, "weight": 3}, {"source": 4285, "target": 4485, "weight": 3}, {"source": 4286, "target": 4486, "weight": 3}, {"source": 4286, "target": 4086, "weight": 3}, {"source": 4286, "target": 4287, "weight": 3}, {"source": 4287, "target": 4288, "weight": 2}, {"source": 4287, "target": 4487, "weight": 2}, {"source": 4287, "target": 4087, "weight": 2}, {"source": 4288, "target": 4088, "weight": 3}, {"source": 4288, "target": 4289, "weight": 2}, {"source": 4288, "target": 4488, "weight": 2}, {"source": 4289, "target": 4089, "weight": 2}, {"source": 4289, "target": 4489, "weight": 2}, {"source": 5880, "target": 5881, "weight": 3}, {"source": 5881, "target": 5882, "weight": 3}, {"source": 5882, "target": 5883, "weight": 3}, {"source": 5883, "target": 5884, "weight": 3}, {"source": 5884, "target": 5885, "weight": 3}, {"source": 5885, "target": 5886, "weight": 3}, {"source": 5886, "target": 5887, "weight": 3}, {"source": 5887, "target": 5888, "weight": 3}, {"source": 5888, "target": 5889, "weight": 3}, {"source": 4880, "target": 4881, "weight": 3}, {"source": 4880, "target": 5080, "weight": 3}, {"source": 4881, "target": 4882, "weight": 3}, {"source": 4881, "target": 5081, "weight": 3}, {"source": 4882, "target": 4883, "weight": 2}, {"source": 4882, "target": 5082, "weight": 3}, {"source": 4883, "target": 4884, "weight": 3}, {"source": 4883, "target": 5083, "weight": 3}, {"source": 4884, "target": 5084, "weight": 3}, {"source": 4884, "target": 4885, "weight": 3}, {"source": 4885, "target": 4886, "weight": 2}, {"source": 4885, "target": 5085, "weight": 2}, {"source": 4886, "target": 5086, "weight": 3}, {"source": 4886, "target": 4887, "weight": 3}, {"source": 4887, "target": 4888, "weight": 3}, {"source": 4887, "target": 5087, "weight": 3}, {"source": 4888, "target": 4889, "weight": 3}, {"source": 4888, "target": 5088, "weight": 3}, {"source": 4889, "target": 5089, "weight": 3}, {"source": 5480, "target": 5481, "weight": 3}, {"source": 5481, "target": 5482, "weight": 3}, {"source": 5482, "target": 5483, "weight": 3}, {"source": 5483, "target": 5484, "weight": 2}, {"source": 5484, "target": 5485, "weight": 3}, {"source": 5485, "target": 5486, "weight": 3}, {"source": 5486, "target": 5487, "weight": 2}, {"source": 5487, "target": 5488, "weight": 2}, {"source": 5488, "target": 5489, "weight": 3}, {"source": 4480, "target": 4481, "weight": 3}, {"source": 4481, "target": 4482, "weight": 3}, {"source": 4482, "target": 4483, "weight": 3}, {"source": 4483, "target": 4484, "weight": 3}, {"source": 4484, "target": 4485, "weight": 3}, {"source": 4485, "target": 4486, "weight": 3}, {"source": 4486, "target": 4487, "weight": 3}, {"source": 4487, "target": 4488, "weight": 2}, {"source": 4488, "target": 4489, "weight": 2}, {"source": 5080, "target": 5081, "weight": 3}, {"source": 5081, "target": 5082, "weight": 3}, {"source": 5082, "target": 5083, "weight": 3}, {"source": 5083, "target": 5084, "weight": 3}, {"source": 5084, "target": 5085, "weight": 2}, {"source": 5085, "target": 5086, "weight": 3}, {"source": 5086, "target": 5087, "weight": 3}, {"source": 5087, "target": 5088, "weight": 3}, {"source": 5088, "target": 5089, "weight": 3}, {"source": 4080, "target": 4081, "weight": 3}, {"source": 4081, "target": 4082, "weight": 3}, {"source": 4082, "target": 4083, "weight": 3}, {"source": 4083, "target": 4084, "weight": 3}, {"source": 4084, "target": 4085, "weight": 3}, {"source": 4085, "target": 4086, "weight": 3}, {"source": 4086, "target": 4087, "weight": 3}, {"source": 4087, "target": 4088, "weight": 3}, {"source": 4088, "target": 4089, "weight": 3}], "multigraph": false}