{"directed": false, "graph": {}, "nodes": [{"level": 2, "edge_list": [{"graph": 349, "neighbor": 19979}, {"graph": 370, "neighbor": 20180}], "edge": true, "y": 18.0, "x": 9.9, "id": 19980}, {"level": 2, "edge_list": [{"graph": 370, "neighbor": 20181}], "edge": true, "y": 18.1, "x": 9.9, "id": 19981}, {"level": 1, "edge_list": [{"graph": 370, "neighbor": 20182}], "edge": true, "y": 18.2, "x": 9.9, "id": 19982}, {"level": 2, "edge_list": [{"graph": 370, "neighbor": 20183}], "edge": true, "y": 18.3, "x": 9.9, "id": 19983}, {"level": 2, "edge_list": [{"graph": 370, "neighbor": 20184}], "edge": true, "y": 18.400000000000002, "x": 9.9, "id": 19984}, {"level": 2, "edge_list": [{"graph": 370, "neighbor": 20185}], "edge": true, "y": 18.5, "x": 9.9, "id": 19985}, {"level": 1, "edge_list": [{"graph": 370, "neighbor": 20186}], "edge": true, "y": 18.6, "x": 9.9, "id": 19986}, {"level": 1, "edge_list": [{"graph": 370, "neighbor": 20187}], "edge": true, "y": 18.7, "x": 9.9, "id": 19987}, {"level": 1, "edge_list": [{"graph": 370, "neighbor": 20188}], "edge": true, "y": 18.8, "x": 9.9, "id": 19988}, {"level": 1, "edge_list": [{"graph": 389, "neighbor": 19990}, {"graph": 370, "neighbor": 20189}], "edge": true, "y": 18.900000000000002, "x": 9.9, "id": 19989}, {"level": 3, "edge_list": [{"graph": 349, "neighbor": 18979}], "edge": true, "y": 18.0, "x": 9.4, "id": 18980}, {"y": 18.1, "x": 9.4, "edge": false, "id": 18981, "level": 2}, {"y": 18.2, "x": 9.4, "edge": false, "id": 18982, "level": 2}, {"y": 18.3, "x": 9.4, "edge": false, "id": 18983, "level": 2}, {"y": 18.400000000000002, "x": 9.4, "edge": false, "id": 18984, "level": 2}, {"y": 18.5, "x": 9.4, "edge": false, "id": 18985, "level": 2}, {"y": 18.6, "x": 9.4, "edge": false, "id": 18986, "level": 2}, {"y": 18.7, "x": 9.4, "edge": false, "id": 18987, "level": 2}, {"y": 18.8, "x": 9.4, "edge": false, "id": 18988, "level": 2}, {"level": 2, "edge_list": [{"graph": 389, "neighbor": 18990}], "edge": true, "y": 18.900000000000002, "x": 9.4, "id": 18989}, {"level": 2, "edge_list": [{"graph": 349, "neighbor": 19579}], "edge": true, "y": 18.0, "x": 9.700000000000001, "id": 19580}, {"y": 18.1, "x": 9.700000000000001, "edge": false, "id": 19581, "level": 2}, {"y": 18.2, "x": 9.700000000000001, "edge": false, "id": 19582, "level": 2}, {"y": 18.3, "x": 9.700000000000001, "edge": false, "id": 19583, "level": 2}, {"y": 18.400000000000002, "x": 9.700000000000001, "edge": false, "id": 19584, "level": 2}, {"y": 18.5, "x": 9.700000000000001, "edge": false, "id": 19585, "level": 2}, {"y": 18.6, "x": 9.700000000000001, "edge": false, "id": 19586, "level": 2}, {"y": 18.7, "x": 9.700000000000001, "edge": false, "id": 19587, "level": 1}, {"y": 18.8, "x": 9.700000000000001, "edge": false, "id": 19588, "level": 1}, {"level": 1, "edge_list": [{"graph": 389, "neighbor": 19590}], "edge": true, "y": 18.900000000000002, "x": 9.700000000000001, "id": 19589}, {"level": 2, "edge_list": [{"graph": 349, "neighbor": 18579}], "edge": true, "y": 18.0, "x": 9.200000000000001, "id": 18580}, {"y": 18.1, "x": 9.200000000000001, "edge": false, "id": 18581, "level": 2}, {"y": 18.2, "x": 9.200000000000001, "edge": false, "id": 18582, "level": 2}, {"y": 18.3, "x": 9.200000000000001, "edge": false, "id": 18583, "level": 2}, {"y": 18.400000000000002, "x": 9.200000000000001, "edge": false, "id": 18584, "level": 2}, {"y": 18.5, "x": 9.200000000000001, "edge": false, "id": 18585, "level": 2}, {"y": 18.6, "x": 9.200000000000001, "edge": false, "id": 18586, "level": 2}, {"y": 18.7, "x": 9.200000000000001, "edge": false, "id": 18587, "level": 2}, {"y": 18.8, "x": 9.200000000000001, "edge": false, "id": 18588, "level": 2}, {"level": 2, "edge_list": [{"graph": 389, "neighbor": 18590}], "edge": true, "y": 18.900000000000002, "x": 9.200000000000001, "id": 18589}, {"level": 2, "edge_list": [{"graph": 349, "neighbor": 19179}], "edge": true, "y": 18.0, "x": 9.5, "id": 19180}, {"y": 18.1, "x": 9.5, "edge": false, "id": 19181, "level": 2}, {"y": 18.2, "x": 9.5, "edge": false, "id": 19182, "level": 2}, {"y": 18.3, "x": 9.5, "edge": false, "id": 19183, "level": 2}, {"y": 18.400000000000002, "x": 9.5, "edge": false, "id": 19184, "level": 2}, {"y": 18.5, "x": 9.5, "edge": false, "id": 19185, "level": 2}, {"y": 18.6, "x": 9.5, "edge": false, "id": 19186, "level": 2}, {"y": 18.7, "x": 9.5, "edge": false, "id": 19187, "level": 1}, {"y": 18.8, "x": 9.5, "edge": false, "id": 19188, "level": 1}, {"level": 2, "edge_list": [{"graph": 389, "neighbor": 19190}], "edge": true, "y": 18.900000000000002, "x": 9.5, "id": 19189}, {"level": 3, "edge_list": [{"graph": 349, "neighbor": 18179}, {"graph": 368, "neighbor": 17980}], "edge": true, "y": 18.0, "x": 9.0, "id": 18180}, {"level": 3, "edge_list": [{"graph": 368, "neighbor": 17981}], "edge": true, "y": 18.1, "x": 9.0, "id": 18181}, {"level": 3, "edge_list": [{"graph": 368, "neighbor": 17982}], "edge": true, "y": 18.2, "x": 9.0, "id": 18182}, {"level": 2, "edge_list": [{"graph": 368, "neighbor": 17983}], "edge": true, "y": 18.3, "x": 9.0, "id": 18183}, {"level": 2, "edge_list": [{"graph": 368, "neighbor": 17984}], "edge": true, "y": 18.400000000000002, "x": 9.0, "id": 18184}, {"level": 2, "edge_list": [{"graph": 368, "neighbor": 17985}], "edge": true, "y": 18.5, "x": 9.0, "id": 18185}, {"level": 2, "edge_list": [{"graph": 368, "neighbor": 17986}], "edge": true, "y": 18.6, "x": 9.0, "id": 18186}, {"level": 2, "edge_list": [{"graph": 368, "neighbor": 17987}], "edge": true, "y": 18.7, "x": 9.0, "id": 18187}, {"level": 2, "edge_list": [{"graph": 368, "neighbor": 17988}], "edge": true, "y": 18.8, "x": 9.0, "id": 18188}, {"level": 2, "edge_list": [{"graph": 368, "neighbor": 17989}, {"graph": 389, "neighbor": 18190}], "edge": true, "y": 18.900000000000002, "x": 9.0, "id": 18189}, {"level": 2, "edge_list": [{"graph": 349, "neighbor": 19779}], "edge": true, "y": 18.0, "x": 9.8, "id": 19780}, {"y": 18.1, "x": 9.8, "edge": false, "id": 19781, "level": 2}, {"y": 18.2, "x": 9.8, "edge": false, "id": 19782, "level": 2}, {"y": 18.3, "x": 9.8, "edge": false, "id": 19783, "level": 2}, {"y": 18.400000000000002, "x": 9.8, "edge": false, "id": 19784, "level": 2}, {"y": 18.5, "x": 9.8, "edge": false, "id": 19785, "level": 2}, {"y": 18.6, "x": 9.8, "edge": false, "id": 19786, "level": 2}, {"y": 18.7, "x": 9.8, "edge": false, "id": 19787, "level": 1}, {"y": 18.8, "x": 9.8, "edge": false, "id": 19788, "level": 1}, {"level": 1, "edge_list": [{"graph": 389, "neighbor": 19790}], "edge": true, "y": 18.900000000000002, "x": 9.8, "id": 19789}, {"level": 3, "edge_list": [{"graph": 349, "neighbor": 18779}], "edge": true, "y": 18.0, "x": 9.3, "id": 18780}, {"y": 18.1, "x": 9.3, "edge": false, "id": 18781, "level": 3}, {"y": 18.2, "x": 9.3, "edge": false, "id": 18782, "level": 2}, {"y": 18.3, "x": 9.3, "edge": false, "id": 18783, "level": 2}, {"y": 18.400000000000002, "x": 9.3, "edge": false, "id": 18784, "level": 2}, {"y": 18.5, "x": 9.3, "edge": false, "id": 18785, "level": 2}, {"y": 18.6, "x": 9.3, "edge": false, "id": 18786, "level": 2}, {"y": 18.7, "x": 9.3, "edge": false, "id": 18787, "level": 2}, {"y": 18.8, "x": 9.3, "edge": false, "id": 18788, "level": 2}, {"level": 2, "edge_list": [{"graph": 389, "neighbor": 18790}], "edge": true, "y": 18.900000000000002, "x": 9.3, "id": 18789}, {"level": 2, "edge_list": [{"graph": 349, "neighbor": 19379}], "edge": true, "y": 18.0, "x": 9.600000000000001, "id": 19380}, {"y": 18.1, "x": 9.600000000000001, "edge": false, "id": 19381, "level": 2}, {"y": 18.2, "x": 9.600000000000001, "edge": false, "id": 19382, "level": 2}, {"y": 18.3, "x": 9.600000000000001, "edge": false, "id": 19383, "level": 2}, {"y": 18.400000000000002, "x": 9.600000000000001, "edge": false, "id": 19384, "level": 2}, {"y": 18.5, "x": 9.600000000000001, "edge": false, "id": 19385, "level": 2}, {"y": 18.6, "x": 9.600000000000001, "edge": false, "id": 19386, "level": 2}, {"y": 18.7, "x": 9.600000000000001, "edge": false, "id": 19387, "level": 1}, {"y": 18.8, "x": 9.600000000000001, "edge": false, "id": 19388, "level": 1}, {"level": 1, "edge_list": [{"graph": 389, "neighbor": 19390}], "edge": true, "y": 18.900000000000002, "x": 9.600000000000001, "id": 19389}, {"level": 2, "edge_list": [{"graph": 349, "neighbor": 18379}], "edge": true, "y": 18.0, "x": 9.1, "id": 18380}, {"y": 18.1, "x": 9.1, "edge": false, "id": 18381, "level": 3}, {"y": 18.2, "x": 9.1, "edge": false, "id": 18382, "level": 2}, {"y": 18.3, "x": 9.1, "edge": false, "id": 18383, "level": 2}, {"y": 18.400000000000002, "x": 9.1, "edge": false, "id": 18384, "level": 2}, {"y": 18.5, "x": 9.1, "edge": false, "id": 18385, "level": 2}, {"y": 18.6, "x": 9.1, "edge": false, "id": 18386, "level": 2}, {"y": 18.7, "x": 9.1, "edge": false, "id": 18387, "level": 2}, {"y": 18.8, "x": 9.1, "edge": false, "id": 18388, "level": 2}, {"level": 2, "edge_list": [{"graph": 389, "neighbor": 18390}], "edge": true, "y": 18.900000000000002, "x": 9.1, "id": 18389}], "links": [{"source": 19980, "target": 19780, "weight": 2}, {"source": 19980, "target": 19981, "weight": 2}, {"source": 19981, "target": 19781, "weight": 2}, {"source": 19981, "target": 19982, "weight": 2}, {"source": 19982, "target": 19782, "weight": 2}, {"source": 19982, "target": 19983, "weight": 2}, {"source": 19983, "target": 19984, "weight": 2}, {"source": 19983, "target": 19783, "weight": 2}, {"source": 19984, "target": 19784, "weight": 2}, {"source": 19984, "target": 19985, "weight": 2}, {"source": 19985, "target": 19785, "weight": 2}, {"source": 19985, "target": 19986, "weight": 2}, {"source": 19986, "target": 19786, "weight": 2}, {"source": 19986, "target": 19987, "weight": 1}, {"source": 19987, "target": 19787, "weight": 1}, {"source": 19987, "target": 19988, "weight": 1}, {"source": 19988, "target": 19788, "weight": 1}, {"source": 19988, "target": 19989, "weight": 1}, {"source": 19989, "target": 19789, "weight": 1}, {"source": 18980, "target": 19180, "weight": 3}, {"source": 18980, "target": 18780, "weight": 3}, {"source": 18980, "target": 18981, "weight": 3}, {"source": 18981, "target": 18781, "weight": 3}, {"source": 18981, "target": 18982, "weight": 2}, {"source": 18981, "target": 19181, "weight": 2}, {"source": 18982, "target": 19182, "weight": 2}, {"source": 18982, "target": 18782, "weight": 2}, {"source": 18982, "target": 18983, "weight": 2}, {"source": 18983, "target": 18984, "weight": 2}, {"source": 18983, "target": 19183, "weight": 2}, {"source": 18983, "target": 18783, "weight": 2}, {"source": 18984, "target": 18784, "weight": 2}, {"source": 18984, "target": 18985, "weight": 2}, {"source": 18984, "target": 19184, "weight": 2}, {"source": 18985, "target": 18785, "weight": 2}, {"source": 18985, "target": 18986, "weight": 2}, {"source": 18985, "target": 19185, "weight": 2}, {"source": 18986, "target": 18786, "weight": 2}, {"source": 18986, "target": 18987, "weight": 2}, {"source": 18986, "target": 19186, "weight": 2}, {"source": 18987, "target": 18787, "weight": 2}, {"source": 18987, "target": 18988, "weight": 2}, {"source": 18987, "target": 19187, "weight": 2}, {"source": 18988, "target": 19188, "weight": 2}, {"source": 18988, "target": 18788, "weight": 2}, {"source": 18988, "target": 18989, "weight": 2}, {"source": 18989, "target": 18789, "weight": 2}, {"source": 18989, "target": 19189, "weight": 2}, {"source": 19580, "target": 19780, "weight": 2}, {"source": 19580, "target": 19380, "weight": 2}, {"source": 19580, "target": 19581, "weight": 2}, {"source": 19581, "target": 19381, "weight": 2}, {"source": 19581, "target": 19582, "weight": 2}, {"source": 19581, "target": 19781, "weight": 2}, {"source": 19582, "target": 19782, "weight": 2}, {"source": 19582, "target": 19382, "weight": 2}, {"source": 19582, "target": 19583, "weight": 2}, {"source": 19583, "target": 19584, "weight": 2}, {"source": 19583, "target": 19783, "weight": 2}, {"source": 19583, "target": 19383, "weight": 2}, {"source": 19584, "target": 19384, "weight": 2}, {"source": 19584, "target": 19585, "weight": 2}, {"source": 19584, "target": 19784, "weight": 2}, {"source": 19585, "target": 19385, "weight": 2}, {"source": 19585, "target": 19586, "weight": 2}, {"source": 19585, "target": 19785, "weight": 2}, {"source": 19586, "target": 19386, "weight": 2}, {"source": 19586, "target": 19587, "weight": 2}, {"source": 19586, "target": 19786, "weight": 2}, {"source": 19587, "target": 19387, "weight": 1}, {"source": 19587, "target": 19588, "weight": 1}, {"source": 19587, "target": 19787, "weight": 1}, {"source": 19588, "target": 19788, "weight": 1}, {"source": 19588, "target": 19388, "weight": 1}, {"source": 19588, "target": 19589, "weight": 1}, {"source": 19589, "target": 19389, "weight": 1}, {"source": 19589, "target": 19789, "weight": 1}, {"source": 18580, "target": 18780, "weight": 3}, {"source": 18580, "target": 18380, "weight": 2}, {"source": 18580, "target": 18581, "weight": 2}, {"source": 18581, "target": 18381, "weight": 3}, {"source": 18581, "target": 18582, "weight": 2}, {"source": 18581, "target": 18781, "weight": 3}, {"source": 18582, "target": 18782, "weight": 2}, {"source": 18582, "target": 18382, "weight": 2}, {"source": 18582, "target": 18583, "weight": 2}, {"source": 18583, "target": 18584, "weight": 2}, {"source": 18583, "target": 18783, "weight": 2}, {"source": 18583, "target": 18383, "weight": 2}, {"source": 18584, "target": 18384, "weight": 2}, {"source": 18584, "target": 18585, "weight": 2}, {"source": 18584, "target": 18784, "weight": 2}, {"source": 18585, "target": 18385, "weight": 2}, {"source": 18585, "target": 18586, "weight": 2}, {"source": 18585, "target": 18785, "weight": 2}, {"source": 18586, "target": 18386, "weight": 2}, {"source": 18586, "target": 18587, "weight": 2}, {"source": 18586, "target": 18786, "weight": 2}, {"source": 18587, "target": 18787, "weight": 2}, {"source": 18587, "target": 18387, "weight": 2}, {"source": 18587, "target": 18588, "weight": 2}, {"source": 18588, "target": 18788, "weight": 2}, {"source": 18588, "target": 18388, "weight": 2}, {"source": 18588, "target": 18589, "weight": 2}, {"source": 18589, "target": 18389, "weight": 2}, {"source": 18589, "target": 18789, "weight": 2}, {"source": 19180, "target": 19380, "weight": 2}, {"source": 19180, "target": 19181, "weight": 2}, {"source": 19181, "target": 19182, "weight": 2}, {"source": 19181, "target": 19381, "weight": 2}, {"source": 19182, "target": 19183, "weight": 2}, {"source": 19182, "target": 19382, "weight": 2}, {"source": 19183, "target": 19184, "weight": 2}, {"source": 19183, "target": 19383, "weight": 2}, {"source": 19184, "target": 19185, "weight": 2}, {"source": 19184, "target": 19384, "weight": 2}, {"source": 19185, "target": 19186, "weight": 2}, {"source": 19185, "target": 19385, "weight": 2}, {"source": 19186, "target": 19187, "weight": 2}, {"source": 19186, "target": 19386, "weight": 2}, {"source": 19187, "target": 19188, "weight": 1}, {"source": 19187, "target": 19387, "weight": 1}, {"source": 19188, "target": 19388, "weight": 1}, {"source": 19188, "target": 19189, "weight": 2}, {"source": 19189, "target": 19389, "weight": 2}, {"source": 18180, "target": 18380, "weight": 3}, {"source": 18180, "target": 18181, "weight": 3}, {"source": 18181, "target": 18381, "weight": 3}, {"source": 18181, "target": 18182, "weight": 3}, {"source": 18182, "target": 18382, "weight": 3}, {"source": 18182, "target": 18183, "weight": 3}, {"source": 18183, "target": 18184, "weight": 2}, {"source": 18183, "target": 18383, "weight": 2}, {"source": 18184, "target": 18384, "weight": 2}, {"source": 18184, "target": 18185, "weight": 2}, {"source": 18185, "target": 18385, "weight": 2}, {"source": 18185, "target": 18186, "weight": 2}, {"source": 18186, "target": 18386, "weight": 2}, {"source": 18186, "target": 18187, "weight": 2}, {"source": 18187, "target": 18387, "weight": 2}, {"source": 18187, "target": 18188, "weight": 2}, {"source": 18188, "target": 18388, "weight": 2}, {"source": 18188, "target": 18189, "weight": 2}, {"source": 18189, "target": 18389, "weight": 2}, {"source": 19780, "target": 19781, "weight": 2}, {"source": 19781, "target": 19782, "weight": 2}, {"source": 19782, "target": 19783, "weight": 2}, {"source": 19783, "target": 19784, "weight": 2}, {"source": 19784, "target": 19785, "weight": 2}, {"source": 19785, "target": 19786, "weight": 2}, {"source": 19786, "target": 19787, "weight": 2}, {"source": 19787, "target": 19788, "weight": 1}, {"source": 19788, "target": 19789, "weight": 1}, {"source": 18780, "target": 18781, "weight": 3}, {"source": 18781, "target": 18782, "weight": 3}, {"source": 18782, "target": 18783, "weight": 2}, {"source": 18783, "target": 18784, "weight": 2}, {"source": 18784, "target": 18785, "weight": 2}, {"source": 18785, "target": 18786, "weight": 2}, {"source": 18786, "target": 18787, "weight": 2}, {"source": 18787, "target": 18788, "weight": 2}, {"source": 18788, "target": 18789, "weight": 2}, {"source": 19380, "target": 19381, "weight": 2}, {"source": 19381, "target": 19382, "weight": 2}, {"source": 19382, "target": 19383, "weight": 2}, {"source": 19383, "target": 19384, "weight": 2}, {"source": 19384, "target": 19385, "weight": 2}, {"source": 19385, "target": 19386, "weight": 2}, {"source": 19386, "target": 19387, "weight": 2}, {"source": 19387, "target": 19388, "weight": 1}, {"source": 19388, "target": 19389, "weight": 1}, {"source": 18380, "target": 18381, "weight": 3}, {"source": 18381, "target": 18382, "weight": 3}, {"source": 18382, "target": 18383, "weight": 2}, {"source": 18383, "target": 18384, "weight": 2}, {"source": 18384, "target": 18385, "weight": 2}, {"source": 18385, "target": 18386, "weight": 2}, {"source": 18386, "target": 18387, "weight": 2}, {"source": 18387, "target": 18388, "weight": 2}, {"source": 18388, "target": 18389, "weight": 2}], "multigraph": false}